README.rst
setup.cfg
setup.py
bise/__init__.py
bise.catalogueindexer.egg-info/PKG-INFO
bise.catalogueindexer.egg-info/SOURCES.txt
bise.catalogueindexer.egg-info/dependency_links.txt
bise.catalogueindexer.egg-info/entry_points.txt
bise.catalogueindexer.egg-info/namespace_packages.txt
bise.catalogueindexer.egg-info/not-zip-safe
bise.catalogueindexer.egg-info/requires.txt
bise.catalogueindexer.egg-info/top_level.txt
bise/catalogueindexer/__init__.py
bise/catalogueindexer/configure.zcml
bise/catalogueindexer/interfaces.py
bise/catalogueindexer/subscribers.py
bise/catalogueindexer/tests.py
bise/catalogueindexer/adapters/__init__.py
bise/catalogueindexer/adapters/basic.py
bise/catalogueindexer/adapters/configure.zcml
bise/catalogueindexer/browser/__init__.py
bise/catalogueindexer/browser/configure.zcml
bise/catalogueindexer/browser/contentindexer.py
bise/catalogueindexer/browser/controlpanel.py
bise/catalogueindexer/profiles/default/controlpanel.xml
bise/catalogueindexer/profiles/default/metadata.xml
bise/catalogueindexer/profiles/default/registry.xml
docs/HISTORY.txt
docs/INSTALL.txt
docs/LICENSE.GPL
docs/LICENSE.txt