Metadata-Version: 1.1
Name: bise.catalogueindexer
Version: 1.0
Summary: Catalog indexer methods for BISE
Home-page: https://github.com/eea/bise.catalogueindexer
Author: Mikel Larreategi
Author-email: mlarreategi@codesyntax.com
License: GPL
Platform: UNKNOWN
Classifier: Framework :: Plone
Classifier: Programming Language :: Python
